{"lastUsed":1646040324896,"path":"\/Users\/tj\/kte\/java","projectCount":35,"recentFiles":[{"path":"\/Quiz6_06\/src\/com\/javalec\/base","parentWorkspace":"\/Users\/tj\/kte\/java","name":"Main.java","lastModified":1646030949519,"locationURI":"file:\/Users\/tj\/kte\/java\/Quiz6_06\/src\/com\/javalec\/base\/Main.java"},{"path":"\/OOP6_01\/src\/com\/javalec\/base","parentWorkspace":"\/Users\/tj\/kte\/java","name":"Main.java","lastModified":1646040046870,"locationURI":"file:\/Users\/tj\/kte\/java\/OOP6_01\/src\/com\/javalec\/base\/Main.java"},{"path":"\/intString6_01\/src\/com\/javalec\/base","parentWorkspace":"\/Users\/tj\/kte\/java","name":"Main.java","lastModified":1646036131747,"locationURI":"file:\/Users\/tj\/kte\/java\/intString6_01\/src\/com\/javalec\/base\/Main.java"},{"path":"\/Ex03\/src\/com\/javalec\/base","parentWorkspace":"\/Users\/tj\/kte\/java","name":"Main.java","lastModified":1646010246120,"locationURI":"file:\/Users\/tj\/kte\/java\/1week\/5th%20day\/Ex03\/src\/com\/javalec\/base\/Main.java"},{"path":"\/Array03\/src\/com\/javalec\/base","parentWorkspace":"\/Users\/tj\/kte\/java","name":"Main.java","lastModified":1646010246120,"locationURI":"file:\/Users\/tj\/kte\/java\/1week\/5th%20day\/Array03\/src\/com\/javalec\/base\/Main.java"},{"path":"\/Quiz6_05\/src\/com\/javalec\/base","parentWorkspace":"\/Users\/tj\/kte\/java","name":"Main.java","lastModified":1646029045342,"locationURI":"file:\/Users\/tj\/kte\/java\/Quiz6_05\/src\/com\/javalec\/base\/Main.java"},{"path":"\/Ex02\/src\/com\/javalec\/base","parentWorkspace":"\/Users\/tj\/kte\/java","name":"Main.java","lastModified":1646010246120,"locationURI":"file:\/Users\/tj\/kte\/java\/1week\/5th%20day\/Ex02\/src\/com\/javalec\/base\/Main.java"},{"path":"\/Quiz6_04\/src\/com\/javalecc\/base","parentWorkspace":"\/Users\/tj\/kte\/java","name":"Main.java","lastModified":1646028624225,"locationURI":"file:\/Users\/tj\/kte\/java\/Quiz6_04\/src\/com\/javalecc\/base\/Main.java"},{"path":"\/OOP6_02\/src\/com\/javalec\/base","parentWorkspace":"\/Users\/tj\/kte\/java","name":"Sum.java","lastModified":1646040324906,"locationURI":"file:\/Users\/tj\/kte\/java\/OOP6_02\/src\/com\/javalec\/base\/Sum.java"},{"path":"\/Array\/src\/com\/javalec\/base","parentWorkspace":"\/Users\/tj\/kte\/java","name":"Main.java","lastModified":1646010246119,"locationURI":"file:\/Users\/tj\/kte\/java\/1week\/5th%20day\/Array\/src\/com\/javalec\/base\/Main.java"},{"path":"\/Array02\/src\/com\/javalec\/base","parentWorkspace":"\/Users\/tj\/kte\/java","name":"Main.java","lastModified":1646010246119,"locationURI":"file:\/Users\/tj\/kte\/java\/1week\/5th%20day\/Array02\/src\/com\/javalec\/base\/Main.java"},{"path":"\/Login00\/src\/com\/javalec\/base","parentWorkspace":"\/Users\/tj\/kte\/java","name":"Main.java","lastModified":1646010246120,"locationURI":"file:\/Users\/tj\/kte\/java\/1week\/3rd\/Login00\/src\/com\/javalec\/base\/Main.java"},{"path":"\/Ex01\/src\/com\/javalec\/base","parentWorkspace":"\/Users\/tj\/kte\/java","name":"Main.java","lastModified":1646010246120,"locationURI":"file:\/Users\/tj\/kte\/java\/1week\/5th%20day\/Ex01\/src\/com\/javalec\/base\/Main.java"},{"path":"\/OOP6_01\/src\/com\/javalec\/base","parentWorkspace":"\/Users\/tj\/kte\/java","name":"Sum.java","lastModified":1646038540843,"locationURI":"file:\/Users\/tj\/kte\/java\/OOP6_01\/src\/com\/javalec\/base\/Sum.java"},{"path":"\/Array01\/src\/com\/javalec\/base","parentWorkspace":"\/Users\/tj\/kte\/java","name":"Main.java","lastModified":1646010246119,"locationURI":"file:\/Users\/tj\/kte\/java\/1week\/5th%20day\/Array01\/src\/com\/javalec\/base\/Main.java"},{"path":"\/Time6_01\/src\/com\/javalec\/base","parentWorkspace":"\/Users\/tj\/kte\/java","name":"Main.java","lastModified":1646034197966,"locationURI":"file:\/Users\/tj\/kte\/java\/Time6_01\/src\/com\/javalec\/base\/Main.java"},{"path":"\/Quiz6_01\/src\/com\/javalec\/base","parentWorkspace":"\/Users\/tj\/kte\/java","name":"Main.java","lastModified":1646016627651,"locationURI":"file:\/Users\/tj\/kte\/java\/Quiz6_01\/src\/com\/javalec\/base\/Main.java"},{"path":"\/String_01\/src\/com\/javalec\/base","parentWorkspace":"\/Users\/tj\/kte\/java","name":"Main.java","lastModified":1646035754610,"locationURI":"file:\/Users\/tj\/kte\/java\/String_01\/src\/com\/javalec\/base\/Main.java"},{"path":"\/Calender6_01\/src\/com\/javalec\/base","parentWorkspace":"\/Users\/tj\/kte\/java","name":"Main.java","lastModified":1646033847148,"locationURI":"file:\/Users\/tj\/kte\/java\/Calender6_01\/src\/com\/javalec\/base\/Main.java"},{"path":"\/StringBuilder_01\/src\/com\/javalec\/base","parentWorkspace":"\/Users\/tj\/kte\/java","name":"Main.java","lastModified":1646033323777,"locationURI":"file:\/Users\/tj\/kte\/java\/StringBuilder_01\/src\/com\/javalec\/base\/Main.java"},{"path":"\/Quiz6_03\/src\/com\/javalec\/base","parentWorkspace":"\/Users\/tj\/kte\/java","name":"Main.java","lastModified":1646035754610,"locationURI":"file:\/Users\/tj\/kte\/java\/Quiz6_03\/src\/com\/javalec\/base\/Main.java"},{"path":"\/Quiz6_07\/src\/com\/javalec\/base","parentWorkspace":"\/Users\/tj\/kte\/java","name":"Main.java","lastModified":1646037040994,"locationURI":"file:\/Users\/tj\/kte\/java\/Quiz6_07\/src\/com\/javalec\/base\/Main.java"},{"path":"\/OOP6_01\/src\/com\/javalec\/base","parentWorkspace":"\/Users\/tj\/kte\/java","name":"EvenOdd.java","lastModified":1646039974194,"locationURI":"file:\/Users\/tj\/kte\/java\/OOP6_01\/src\/com\/javalec\/base\/EvenOdd.java"},{"path":"\/Random6_01\/src\/com\/javalec\/base","parentWorkspace":"\/Users\/tj\/kte\/java","name":"Main.java","lastModified":1646035748316,"locationURI":"file:\/Users\/tj\/kte\/java\/Random6_01\/src\/com\/javalec\/base\/Main.java"},{"path":"\/OOP6_02\/src\/com\/javalec\/base","parentWorkspace":"\/Users\/tj\/kte\/java","name":"Main.java","lastModified":1646040324932,"locationURI":"file:\/Users\/tj\/kte\/java\/OOP6_02\/src\/com\/javalec\/base\/Main.java"},{"path":"\/Ex04\/src\/com\/javalec\/base","parentWorkspace":"\/Users\/tj\/kte\/java","name":"Main.java","lastModified":1646010246120,"locationURI":"file:\/Users\/tj\/kte\/java\/1week\/5th%20day\/Ex04\/src\/com\/javalec\/base\/Main.java"},{"path":"\/Quiz6_02\/src\/com\/javalec\/base","parentWorkspace":"\/Users\/tj\/kte\/java","name":"Main.java","lastModified":1646035754610,"locationURI":"file:\/Users\/tj\/kte\/java\/Quiz6_02\/src\/com\/javalec\/base\/Main.java"}]}